serial_module/__init__.py
serial_module/base/__init__.py
serial_module/base/mock_serial.py
serial_module/base/real_serial.py
serial_module/base/serial_controller.py
serial_module/data_type/__init__.py
serial_module/data_type/hex_struct.py
serial_module/exception/__init__.py
serial_module/exception/connection_exception.py
serial_module/exception/not_connected_exception.py
serial_module/exception/probe_not_down_exception.py
serial_module/exception/respond_parse_exception.py
serial_module/exception/timeout_exception.py
serial_module/interface/__init__.py
serial_module/interface/serial_interface.py
serial_module-1.1.0.dist-info/METADATA
serial_module-1.1.0.dist-info/WHEEL
serial_module-1.1.0.dist-info/top_level.txt
serial_module-1.1.0.dist-info/RECORD
