Metadata-Version: 2.1
Name: serial-module
Version: 1.1.0
Summary: 串行接口模块简单包装,支持模拟接口和真实接口
Home-page: https://github.com/KD-Group/serial_module
Author: Jefung
Author-email: 865424525@qq.com
License: MIT
Keywords: python serial
Platform: UNKNOWN
Classifier: Programming Language :: Python :: 3
Requires-Python: >=3
Requires-Dist: crcmod
Requires-Dist: pyserial
